<annotation>
	<folder>VOC12Train</folder>
	<filename>20200829160701219_1.mp4_109.jpg</filename>
	<source>
		<database>The UAV autolanding</database>
		<annotation>UAV AutoLanding</annotation>
		<image>flickr</image>
		<flickrid>NULL</flickrid>
	</source>
	<owner>
		<flickrid>NULL</flickrid>
		<name>Liurunxuan</name>
	</owner>
	<size>
		<width>1920</width>
		<height>1080</height>
		<depth>3</depth>
	</size>
		<segmented>0</segmented>
	<object>
		<name>coast</name>
		<pose>Unspecified</pose>
		<truncated>1</truncated>
		<difficult>0</difficult>
		<bndbox>
			<xmin>8.11111111111111</xmin>
			<ymin>472.14814814814815</ymin>
			<xmax>994.5308641975308</xmax>
			<ymax>525.2345679012345</ymax>
		</bndbox>
	</object>
	<object>
		<name>this</name>
		<pose>Unspecified</pose>
		<truncated>1</truncated>
		<difficult>0</difficult>
		<bndbox>
			<xmin>629.0987654320987</xmin>
			<ymin>946.2222222222222</ymin>
			<xmax>1021.0</xmax>
			<ymax>1079.0</ymax>
		</bndbox>
	</object>
</annotation>