<annotation>
	<folder>VOC12Train</folder>
	<filename>20200829155313476.mp4_15.jpg</filename>
	<source>
		<database>The UAV autolanding</database>
		<annotation>UAV AutoLanding</annotation>
		<image>flickr</image>
		<flickrid>NULL</flickrid>
	</source>
	<owner>
		<flickrid>NULL</flickrid>
		<name>Liurunxuan</name>
	</owner>
	<size>
		<width>1920</width>
		<height>1080</height>
		<depth>3</depth>
	</size>
		<segmented>0</segmented>
	<object>
		<name>this</name>
		<pose>Unspecified</pose>
		<truncated>1</truncated>
		<difficult>0</difficult>
		<bndbox>
			<xmin>631.5679012345679</xmin>
			<ymin>957.3333333333333</ymin>
			<xmax>1030.0</xmax>
			<ymax>1079.0</ymax>
		</bndbox>
	</object>
</annotation>